example/__init__.py
example/app.py
example/app_2.py
skywalking_flask/__init__.py
skywalking_flask-0.0.7.dist-info/LICENSE
skywalking_flask-0.0.7.dist-info/METADATA
skywalking_flask-0.0.7.dist-info/WHEEL
skywalking_flask-0.0.7.dist-info/top_level.txt
skywalking_flask-0.0.7.dist-info/RECORD
