Metadata-Version: 2.1
Name: skywalking-flask
Version: 0.0.7
Summary: Skywalking Flask Support.
Home-page: https://gitee.com/parkerzhu/skywalking-flask
Author: Parker Zhu
Author-email: 806000178@qq.com
License: UNKNOWN
Platform: UNKNOWN
Classifier: Programming Language :: Python :: 3
Classifier: License :: OSI Approved :: MIT License
Classifier: Operating System :: OS Independent
Requires-Python: >=3.5
Requires-Dist: flask
Requires-Dist: apache-skywalking (==0.3.0)
Requires-Dist: requests
